setup.py
ezauto/__init__.py
ezauto/ezauto.py
ezauto.egg-info/PKG-INFO
ezauto.egg-info/SOURCES.txt
ezauto.egg-info/dependency_links.txt
ezauto.egg-info/top_level.txt