Metadata-Version: 2.1
Name: ezauto
Version: 0.0.1
Summary: Automated message support - Changes coming soon
Author: Chase
